<annotation>
    <folder>pikachu</folder>
    <filename>train_pikachu_210.png</filename>
    <path>/home/cmf/w_learn/d2l-pytorch/data/pikachu/train_pikachu_210.png</path>
    <source>
        <database>Unknown</database>
    </source>
    <size>
        <width>256</width>
        <height>256</height>
        <depth>3</depth>
    </size>
    <segmented>0</segmented>

    <object>
        <name>pikachu</name>
        <pose>Unspecified</pose>
        <truncated>0</truncated>
        <difficult>0</difficult>
        <bndbox>
            <xmin>105.43960571289062</xmin>
            <ymin>110.41036224365234</ymin>
            <xmax>125.08627319335938</xmax>
            <ymax>141.4159393310547</ymax>
        </bndbox>
    </object>
    
</annotation>
