<annotation>
    <folder>pikachu</folder>
    <filename>train_pikachu_141.png</filename>
    <path>/home/cmf/w_learn/d2l-pytorch/data/pikachu/train_pikachu_141.png</path>
    <source>
        <database>Unknown</database>
    </source>
    <size>
        <width>256</width>
        <height>256</height>
        <depth>3</depth>
    </size>
    <segmented>0</segmented>

    <object>
        <name>pikachu</name>
        <pose>Unspecified</pose>
        <truncated>0</truncated>
        <difficult>0</difficult>
        <bndbox>
            <xmin>127.79581451416016</xmin>
            <ymin>102.82696533203125</ymin>
            <xmax>159.2793731689453</xmax>
            <ymax>145.83738708496094</ymax>
        </bndbox>
    </object>
    
</annotation>
