<annotation>
    <folder>pikachu</folder>
    <filename>train_pikachu_413.png</filename>
    <path>/home/cmf/w_learn/d2l-pytorch/data/pikachu/train_pikachu_413.png</path>
    <source>
        <database>Unknown</database>
    </source>
    <size>
        <width>256</width>
        <height>256</height>
        <depth>3</depth>
    </size>
    <segmented>0</segmented>

    <object>
        <name>pikachu</name>
        <pose>Unspecified</pose>
        <truncated>0</truncated>
        <difficult>0</difficult>
        <bndbox>
            <xmin>100.9036865234375</xmin>
            <ymin>97.4163589477539</ymin>
            <xmax>127.68104553222656</xmax>
            <ymax>133.16688537597656</ymax>
        </bndbox>
    </object>
    
</annotation>
