<annotation>
    <folder>pikachu</folder>
    <filename>train_pikachu_787.png</filename>
    <path>/home/cmf/w_learn/d2l-pytorch/data/pikachu/train_pikachu_787.png</path>
    <source>
        <database>Unknown</database>
    </source>
    <size>
        <width>256</width>
        <height>256</height>
        <depth>3</depth>
    </size>
    <segmented>0</segmented>

    <object>
        <name>pikachu</name>
        <pose>Unspecified</pose>
        <truncated>0</truncated>
        <difficult>0</difficult>
        <bndbox>
            <xmin>147.71315002441406</xmin>
            <ymin>89.22077178955078</ymin>
            <xmax>171.4298553466797</xmax>
            <ymax>124.7520980834961</ymax>
        </bndbox>
    </object>
    
</annotation>
