<annotation>
    <folder>pikachu</folder>
    <filename>train_pikachu_652.png</filename>
    <path>/home/cmf/w_learn/d2l-pytorch/data/pikachu/train_pikachu_652.png</path>
    <source>
        <database>Unknown</database>
    </source>
    <size>
        <width>256</width>
        <height>256</height>
        <depth>3</depth>
    </size>
    <segmented>0</segmented>

    <object>
        <name>pikachu</name>
        <pose>Unspecified</pose>
        <truncated>0</truncated>
        <difficult>0</difficult>
        <bndbox>
            <xmin>100.06499481201172</xmin>
            <ymin>81.345458984375</ymin>
            <xmax>127.1884765625</xmax>
            <ymax>123.88453674316406</ymax>
        </bndbox>
    </object>
    
</annotation>
